{
  "items": [
    {
      "title": "Umbria Volley Perugia (Voleibol) x Warta Zawiercie (Voleibol) - 17/05 19:30 - SportTV 5",
      "link": "http://www.zerozero.pt/zapping",
      "description": "Umbria Volley Perugia (Voleibol) x Warta Zawiercie (Voleibol) - 17/05 19:30 - SportTV 5",
      "pubDate": "Sun, 17 May 2026 19:30:00",
      "guid": ""
    },
    {
      "title": "Paris FC x PSG - 17/05 20:00 - SportTV 3",
      "link": "http://www.zerozero.pt/zapping",
      "description": "Paris FC x PSG - 17/05 20:00 - SportTV 3",
      "pubDate": "Sun, 17 May 2026 20:00:00",
      "guid": ""
    },
    {
      "title": "Lyon x Lens - 17/05 20:00 - SportTV 4",
      "link": "http://www.zerozero.pt/zapping",
      "description": "Lyon x Lens - 17/05 20:00 - SportTV 4",
      "pubDate": "Sun, 17 May 2026 20:00:00",
      "guid": ""
    },
    {
      "title": "Barcelona x Real Betis - 17/05 20:15 - DAZN 1",
      "link": "http://www.zerozero.pt/zapping",
      "description": "Barcelona x Real Betis - 17/05 20:15 - DAZN 1",
      "pubDate": "Sun, 17 May 2026 20:15:00",
      "guid": ""
    },
    {
      "title": "Portimonense x Farense - 17/05 20:30 - SportTV 1",
      "link": "http://www.zerozero.pt/zapping",
      "description": "Portimonense x Farense - 17/05 20:30 - SportTV 1",
      "pubDate": "Sun, 17 May 2026 20:30:00",
      "guid": ""
    },
    {
      "title": "Paços de Ferreira x FC Penafiel - 17/05 20:30 - SportTV 2",
      "link": "http://www.zerozero.pt/zapping",
      "description": "Paços de Ferreira x FC Penafiel - 17/05 20:30 - SportTV 2",
      "pubDate": "Sun, 17 May 2026 20:30:00",
      "guid": ""
    },
    {
      "title": "França (Feminino S16) x Portugal (Feminino S16) - 18/05 16:00 - Canal11",
      "link": "http://www.zerozero.pt/zapping",
      "description": "França (Feminino S16) x Portugal (Feminino S16) - 18/05 16:00 - Canal11",
      "pubDate": "Mon, 18 May 2026 16:00:00",
      "guid": ""
    },
    {
      "title": "Arsenal x Burnley - 18/05 20:00 - DAZN 1",
      "link": "http://www.zerozero.pt/zapping",
      "description": "Arsenal x Burnley - 18/05 20:00 - DAZN 1",
      "pubDate": "Mon, 18 May 2026 20:00:00",
      "guid": ""
    },
    {
      "title": "Bournemouth x Manchester City - 19/05 19:30 - DAZN 1",
      "link": "http://www.zerozero.pt/zapping",
      "description": "Bournemouth x Manchester City - 19/05 19:30 - DAZN 1",
      "pubDate": "Tue, 19 May 2026 19:30:00",
      "guid": ""
    },
    {
      "title": "Chelsea x Tottenham - 19/05 20:15 - DAZN 2",
      "link": "http://www.zerozero.pt/zapping",
      "description": "Chelsea x Tottenham - 19/05 20:15 - DAZN 2",
      "pubDate": "Tue, 19 May 2026 20:15:00",
      "guid": ""
    },
    {
      "title": "Rosario Central x UCV FC - 19/05 23:00 - SportTV 1",
      "link": "http://www.zerozero.pt/zapping",
      "description": "Rosario Central x UCV FC - 19/05 23:00 - SportTV 1",
      "pubDate": "Tue, 19 May 2026 23:00:00",
      "guid": ""
    },
    {
      "title": "Boca Juniors x Cruzeiro - 20/05 01:30 - SportTV 1",
      "link": "http://www.zerozero.pt/zapping",
      "description": "Boca Juniors x Cruzeiro - 20/05 01:30 - SportTV 1",
      "pubDate": "Wed, 20 May 2026 01:30:00",
      "guid": ""
    },
    {
      "title": "Al-Khaleej x Al-Ahli Jeddah - 20/05 19:00 - SportTV 1",
      "link": "http://www.zerozero.pt/zapping",
      "description": "Al-Khaleej x Al-Ahli Jeddah - 20/05 19:00 - SportTV 1",
      "pubDate": "Wed, 20 May 2026 19:00:00",
      "guid": ""
    },
    {
      "title": "SC Freiburg x Aston Villa - 20/05 20:00 - SportTV 5",
      "link": "http://www.zerozero.pt/zapping",
      "description": "SC Freiburg x Aston Villa - 20/05 20:00 - SportTV 5",
      "pubDate": "Wed, 20 May 2026 20:00:00",
      "guid": ""
    },
    {
      "title": "AD Sanjoanense (Hóquei) x Benfica (Hóquei) - 20/05 20:30 - DAZN 2",
      "link": "http://www.zerozero.pt/zapping",
      "description": "AD Sanjoanense (Hóquei) x Benfica (Hóquei) - 20/05 20:30 - DAZN 2",
      "pubDate": "Wed, 20 May 2026 20:30:00",
      "guid": ""
    },
    {
      "title": "UD Oliveirense (Hóquei) x FC Porto (Hóquei) - 20/05 21:00 - PortoCanal",
      "link": "http://www.zerozero.pt/zapping",
      "description": "UD Oliveirense (Hóquei) x FC Porto (Hóquei) - 20/05 21:00 - PortoCanal",
      "pubDate": "Wed, 20 May 2026 21:00:00",
      "guid": ""
    },
    {
      "title": "Talleres x Atlético Tucumán - 20/05 21:00 - SportTV 2",
      "link": "http://www.zerozero.pt/zapping",
      "description": "Talleres x Atlético Tucumán - 20/05 21:00 - SportTV 2",
      "pubDate": "Wed, 20 May 2026 21:00:00",
      "guid": ""
    },
    {
      "title": "Santos x San Lorenzo - 20/05 23:00 - SportTV 1",
      "link": "http://www.zerozero.pt/zapping",
      "description": "Santos x San Lorenzo - 20/05 23:00 - SportTV 1",
      "pubDate": "Wed, 20 May 2026 23:00:00",
      "guid": ""
    },
    {
      "title": "Grêmio x Palestino - 21/05 01:00 - SportTV 4",
      "link": "http://www.zerozero.pt/zapping",
      "description": "Grêmio x Palestino - 21/05 01:00 - SportTV 4",
      "pubDate": "Thu, 21 May 2026 01:00:00",
      "guid": ""
    },
    {
      "title": "Independiente Petrolero x Botafogo - 21/05 01:00 - SportTV 3",
      "link": "http://www.zerozero.pt/zapping",
      "description": "Independiente Petrolero x Botafogo - 21/05 01:00 - SportTV 3",
      "pubDate": "Thu, 21 May 2026 01:00:00",
      "guid": ""
    },
    {
      "title": "Palmeiras x Cerro Porteño - 21/05 01:30 - SportTV 1",
      "link": "http://www.zerozero.pt/zapping",
      "description": "Palmeiras x Cerro Porteño - 21/05 01:30 - SportTV 1",
      "pubDate": "Thu, 21 May 2026 01:30:00",
      "guid": ""
    },
    {
      "title": "River Plate x Red Bull Bragantino - 21/05 01:30 - SportTV 5",
      "link": "http://www.zerozero.pt/zapping",
      "description": "River Plate x Red Bull Bragantino - 21/05 01:30 - SportTV 5",
      "pubDate": "Thu, 21 May 2026 01:30:00",
      "guid": ""
    },
    {
      "title": "Al-Fayha x Al-Hilal - 21/05 19:00 - SportTV 2",
      "link": "http://www.zerozero.pt/zapping",
      "description": "Al-Fayha x Al-Hilal - 21/05 19:00 - SportTV 2",
      "pubDate": "Thu, 21 May 2026 19:00:00",
      "guid": ""
    },
    {
      "title": "Al-Nassr x Damac FC - 21/05 19:00 - SportTV 1",
      "link": "http://www.zerozero.pt/zapping",
      "description": "Al-Nassr x Damac FC - 21/05 19:00 - SportTV 1",
      "pubDate": "Thu, 21 May 2026 19:00:00",
      "guid": ""
    },
    {
      "title": "Peñarol x Corinthians - 22/05 01:30 - SportTV 1",
      "link": "http://www.zerozero.pt/zapping",
      "description": "Peñarol x Corinthians - 22/05 01:30 - SportTV 1",
      "pubDate": "Fri, 22 May 2026 01:30:00",
      "guid": ""
    },
    {
      "title": "Montpellier (Jun.A S18) x PSG (Jun.A S18) - 22/05 15:15 - SportTV 2",
      "link": "http://www.zerozero.pt/zapping",
      "description": "Montpellier (Jun.A S18) x PSG (Jun.A S18) - 22/05 15:15 - SportTV 2",
      "pubDate": "Fri, 22 May 2026 15:15:00",
      "guid": ""
    },
    {
      "title": "Olympiacos (Basket) x Fenerbahçe (Basket) - 22/05 16:00 - SportTV 7",
      "link": "http://www.zerozero.pt/zapping",
      "description": "Olympiacos (Basket) x Fenerbahçe (Basket) - 22/05 16:00 - SportTV 7",
      "pubDate": "Fri, 22 May 2026 16:00:00",
      "guid": ""
    },
    {
      "title": "Valencia Basket (Basket) x Real Madrid - 22/05 19:00 - SportTV 7",
      "link": "http://www.zerozero.pt/zapping",
      "description": "Valencia Basket (Basket) x Real Madrid - 22/05 19:00 - SportTV 7",
      "pubDate": "Fri, 22 May 2026 19:00:00",
      "guid": ""
    },
    {
      "title": "Lens x Nice - 22/05 20:00 - SportTV 1",
      "link": "http://www.zerozero.pt/zapping",
      "description": "Lens x Nice - 22/05 20:00 - SportTV 1",
      "pubDate": "Fri, 22 May 2026 20:00:00",
      "guid": ""
    },
    {
      "title": "Valadares Gaia (Feminino) x FC Porto (Feminino) - 23/05 11:00 - Canal11",
      "link": "http://www.zerozero.pt/zapping",
      "description": "Valadares Gaia (Feminino) x FC Porto (Feminino) - 23/05 11:00 - Canal11",
      "pubDate": "Sat, 23 May 2026 11:00:00",
      "guid": ""
    },
    {
      "title": "Celtic x Dunfermline - 23/05 15:00 - SportTV 2",
      "link": "http://www.zerozero.pt/zapping",
      "description": "Celtic x Dunfermline - 23/05 15:00 - SportTV 2",
      "pubDate": "Sat, 23 May 2026 15:00:00",
      "guid": ""
    },
    {
      "title": "Hull City x Southampton - 23/05 16:30 - SportTV 2",
      "link": "http://www.zerozero.pt/zapping",
      "description": "Hull City x Southampton - 23/05 16:30 - SportTV 2",
      "pubDate": "Sat, 23 May 2026 16:30:00",
      "guid": ""
    },
    {
      "title": "Barcelona (Feminino) x OL Lyonnes (Feminino) - 23/05 17:00 - RTP2",
      "link": "http://www.zerozero.pt/zapping",
      "description": "Barcelona (Feminino) x OL Lyonnes (Feminino) - 23/05 17:00 - RTP2",
      "pubDate": "Sat, 23 May 2026 17:00:00",
      "guid": ""
    },
    {
      "title": "Benfica (Futsal Feminino) x Nun´Álvares (Futsal Feminino) - 23/05 21:00 - Canal11",
      "link": "http://www.zerozero.pt/zapping",
      "description": "Benfica (Futsal Feminino) x Nun´Álvares (Futsal Feminino) - 23/05 21:00 - Canal11",
      "pubDate": "Sat, 23 May 2026 21:00:00",
      "guid": ""
    }
  ]
}