{
  "items": [
    {
      "title": "AD Marco 09 x AD Sanjoanense - 29/11 11:00 - Canal11",
      "link": "http://www.zerozero.pt/zapping",
      "description": "AD Marco 09 x AD Sanjoanense - 29/11 11:00 - Canal11",
      "pubDate": "Sat, 29 Nov 2025 11:00:00",
      "guid": ""
    },
    {
      "title": "Académico x FC Penafiel - 29/11 11:00 - SportTV 1",
      "link": "http://www.zerozero.pt/zapping",
      "description": "Académico x FC Penafiel - 29/11 11:00 - SportTV 1",
      "pubDate": "Sat, 29 Nov 2025 11:00:00",
      "guid": ""
    },
    {
      "title": "Panamá (Futsal Feminino) x Brasil (Futsal Feminino) - 29/11 11:30 - RTP2",
      "link": "http://www.zerozero.pt/zapping",
      "description": "Panamá (Futsal Feminino) x Brasil (Futsal Feminino) - 29/11 11:30 - RTP2",
      "pubDate": "Sat, 29 Nov 2025 11:30:00",
      "guid": ""
    },
    {
      "title": "Holstein Kiel x Hertha BSC - 29/11 12:00 - DAZN 1",
      "link": "http://www.zerozero.pt/zapping",
      "description": "Holstein Kiel x Hertha BSC - 29/11 12:00 - DAZN 1",
      "pubDate": "Sat, 29 Nov 2025 12:00:00",
      "guid": ""
    },
    {
      "title": "Leicester City x Sheffield United - 29/11 12:30 - SportTV 3",
      "link": "http://www.zerozero.pt/zapping",
      "description": "Leicester City x Sheffield United - 29/11 12:30 - SportTV 3",
      "pubDate": "Sat, 29 Nov 2025 12:30:00",
      "guid": ""
    },
    {
      "title": "Mallorca x Osasuna - 29/11 13:00 - DAZN 2",
      "link": "http://www.zerozero.pt/zapping",
      "description": "Mallorca x Osasuna - 29/11 13:00 - DAZN 2",
      "pubDate": "Sat, 29 Nov 2025 13:00:00",
      "guid": ""
    },
    {
      "title": "UD Oliveirense x Leixões - 29/11 14:00 - SportTV +",
      "link": "http://www.zerozero.pt/zapping",
      "description": "UD Oliveirense x Leixões - 29/11 14:00 - SportTV +",
      "pubDate": "Sat, 29 Nov 2025 14:00:00",
      "guid": ""
    },
    {
      "title": "Parma x Udinese - 29/11 14:00 - SportTV 2",
      "link": "http://www.zerozero.pt/zapping",
      "description": "Parma x Udinese - 29/11 14:00 - SportTV 2",
      "pubDate": "Sat, 29 Nov 2025 14:00:00",
      "guid": ""
    },
    {
      "title": "Bayern München x FC St. Pauli - 29/11 14:30 - DAZN 3",
      "link": "http://www.zerozero.pt/zapping",
      "description": "Bayern München x FC St. Pauli - 29/11 14:30 - DAZN 3",
      "pubDate": "Sat, 29 Nov 2025 14:30:00",
      "guid": ""
    },
    {
      "title": "Fafe x USC Paredes - 29/11 15:00 - C11 Stream",
      "link": "http://www.zerozero.pt/zapping",
      "description": "Fafe x USC Paredes - 29/11 15:00 - C11 Stream",
      "pubDate": "Sat, 29 Nov 2025 15:00:00",
      "guid": ""
    },
    {
      "title": "S. João Ver x Varzim - 29/11 15:00 - C11 Stream",
      "link": "http://www.zerozero.pt/zapping",
      "description": "S. João Ver x Varzim - 29/11 15:00 - C11 Stream",
      "pubDate": "Sat, 29 Nov 2025 15:00:00",
      "guid": ""
    },
    {
      "title": "Amarante FC x Vitória SC - 29/11 15:00 - C11 Stream",
      "link": "http://www.zerozero.pt/zapping",
      "description": "Amarante FC x Vitória SC - 29/11 15:00 - C11 Stream",
      "pubDate": "Sat, 29 Nov 2025 15:00:00",
      "guid": ""
    },
    {
      "title": "Portugal (Feminino S17) x Bulgária (Feminino S17) - 29/11 15:00 - Canal11",
      "link": "http://www.zerozero.pt/zapping",
      "description": "Portugal (Feminino S17) x Bulgária (Feminino S17) - 29/11 15:00 - Canal11",
      "pubDate": "Sat, 29 Nov 2025 15:00:00",
      "guid": ""
    },
    {
      "title": "Manchester City x Leeds United - 29/11 15:00 - DAZN 1",
      "link": "http://www.zerozero.pt/zapping",
      "description": "Manchester City x Leeds United - 29/11 15:00 - DAZN 1",
      "pubDate": "Sat, 29 Nov 2025 15:00:00",
      "guid": ""
    },
    {
      "title": "Sunderland x Bournemouth - 29/11 15:00 - DAZN 4",
      "link": "http://www.zerozero.pt/zapping",
      "description": "Sunderland x Bournemouth - 29/11 15:00 - DAZN 4",
      "pubDate": "Sat, 29 Nov 2025 15:00:00",
      "guid": ""
    },
    {
      "title": "ABC (Andebol) x Belenenses (Andebol) - 29/11 15:00 - ABola TV",
      "link": "http://www.zerozero.pt/zapping",
      "description": "ABC (Andebol) x Belenenses (Andebol) - 29/11 15:00 - ABola TV",
      "pubDate": "Sat, 29 Nov 2025 15:00:00",
      "guid": ""
    },
    {
      "title": "Sporting (Voleibol) x Ala Nun´Álvares (Voleibol) - 29/11 15:00 - SportingTv",
      "link": "http://www.zerozero.pt/zapping",
      "description": "Sporting (Voleibol) x Ala Nun´Álvares (Voleibol) - 29/11 15:00 - SportingTv",
      "pubDate": "Sat, 29 Nov 2025 15:00:00",
      "guid": ""
    },
    {
      "title": "West Bromwich x Swansea City - 29/11 15:00 - SportTV 6",
      "link": "http://www.zerozero.pt/zapping",
      "description": "West Bromwich x Swansea City - 29/11 15:00 - SportTV 6",
      "pubDate": "Sat, 29 Nov 2025 15:00:00",
      "guid": ""
    },
    {
      "title": "Barcelona x Alavés - 29/11 15:15 - DAZN 2",
      "link": "http://www.zerozero.pt/zapping",
      "description": "Barcelona x Alavés - 29/11 15:15 - DAZN 2",
      "pubDate": "Sat, 29 Nov 2025 15:15:00",
      "guid": ""
    },
    {
      "title": "Moreirense x FC Famalicão - 29/11 15:30 - V+",
      "link": "http://www.zerozero.pt/zapping",
      "description": "Moreirense x FC Famalicão - 29/11 15:30 - V+",
      "pubDate": "Sat, 29 Nov 2025 15:30:00",
      "guid": ""
    },
    {
      "title": "Casa Pia AC x FC Alverca - 29/11 15:30 - SportTV 1",
      "link": "http://www.zerozero.pt/zapping",
      "description": "Casa Pia AC x FC Alverca - 29/11 15:30 - SportTV 1",
      "pubDate": "Sat, 29 Nov 2025 15:30:00",
      "guid": ""
    },
    {
      "title": "Monaco x PSG - 29/11 16:00 - SportTV 3",
      "link": "http://www.zerozero.pt/zapping",
      "description": "Monaco x PSG - 29/11 16:00 - SportTV 3",
      "pubDate": "Sat, 29 Nov 2025 16:00:00",
      "guid": ""
    },
    {
      "title": "Vitória SC (Andebol) x Artística de Avanca (Andebol) - 29/11 16:00 - AndebolTV",
      "link": "http://www.zerozero.pt/zapping",
      "description": "Vitória SC (Andebol) x Artística de Avanca (Andebol) - 29/11 16:00 - AndebolTV",
      "pubDate": "Sat, 29 Nov 2025 16:00:00",
      "guid": ""
    },
    {
      "title": "U. Santarém x Académica OAF - 29/11 17:00 - C11 Stream",
      "link": "http://www.zerozero.pt/zapping",
      "description": "U. Santarém x Académica OAF - 29/11 17:00 - C11 Stream",
      "pubDate": "Sat, 29 Nov 2025 17:00:00",
      "guid": ""
    },
    {
      "title": "Académica (Hóquei) x FC Porto (Hóquei) - 29/11 17:00 - PortoCanal",
      "link": "http://www.zerozero.pt/zapping",
      "description": "Académica (Hóquei) x FC Porto (Hóquei) - 29/11 17:00 - PortoCanal",
      "pubDate": "Sat, 29 Nov 2025 17:00:00",
      "guid": ""
    },
    {
      "title": "Juventus x Cagliari - 29/11 17:00 - SportTV 2",
      "link": "http://www.zerozero.pt/zapping",
      "description": "Juventus x Cagliari - 29/11 17:00 - SportTV 2",
      "pubDate": "Sat, 29 Nov 2025 17:00:00",
      "guid": ""
    },
    {
      "title": "Trabzonspor x Konyaspor - 29/11 17:00 - SportTV 5",
      "link": "http://www.zerozero.pt/zapping",
      "description": "Trabzonspor x Konyaspor - 29/11 17:00 - SportTV 5",
      "pubDate": "Sat, 29 Nov 2025 17:00:00",
      "guid": ""
    },
    {
      "title": "Al-Ittihad Jeddah x Al-Shabab - 29/11 17:30 - SportTV 4",
      "link": "http://www.zerozero.pt/zapping",
      "description": "Al-Ittihad Jeddah x Al-Shabab - 29/11 17:30 - SportTV 4",
      "pubDate": "Sat, 29 Nov 2025 17:30:00",
      "guid": ""
    },
    {
      "title": "Portugal (Feminino S19) x Islândia (Feminino S19) - 29/11 17:30 - Canal11",
      "link": "http://www.zerozero.pt/zapping",
      "description": "Portugal (Feminino S19) x Islândia (Feminino S19) - 29/11 17:30 - Canal11",
      "pubDate": "Sat, 29 Nov 2025 17:30:00",
      "guid": ""
    },
    {
      "title": "Everton x Newcastle - 29/11 17:30 - DAZN 1",
      "link": "http://www.zerozero.pt/zapping",
      "description": "Everton x Newcastle - 29/11 17:30 - DAZN 1",
      "pubDate": "Sat, 29 Nov 2025 17:30:00",
      "guid": ""
    },
    {
      "title": "Levante x Athletic Bilbao - 29/11 17:30 - DAZN 2",
      "link": "http://www.zerozero.pt/zapping",
      "description": "Levante x Athletic Bilbao - 29/11 17:30 - DAZN 2",
      "pubDate": "Sat, 29 Nov 2025 17:30:00",
      "guid": ""
    },
    {
      "title": "Bayer Leverkusen x Borussia Dortmund - 29/11 17:30 - DAZN 3",
      "link": "http://www.zerozero.pt/zapping",
      "description": "Bayer Leverkusen x Borussia Dortmund - 29/11 17:30 - DAZN 3",
      "pubDate": "Sat, 29 Nov 2025 17:30:00",
      "guid": ""
    },
    {
      "title": "Albacete x Deportivo - 29/11 17:30 - DAZN 4",
      "link": "http://www.zerozero.pt/zapping",
      "description": "Albacete x Deportivo - 29/11 17:30 - DAZN 4",
      "pubDate": "Sat, 29 Nov 2025 17:30:00",
      "guid": ""
    },
    {
      "title": "Nacional x Benfica - 29/11 18:00 - SportTV 1",
      "link": "http://www.zerozero.pt/zapping",
      "description": "Nacional x Benfica - 29/11 18:00 - SportTV 1",
      "pubDate": "Sat, 29 Nov 2025 18:00:00",
      "guid": ""
    },
    {
      "title": "Paris FC x Auxerre - 29/11 18:00 - SportTV 3",
      "link": "http://www.zerozero.pt/zapping",
      "description": "Paris FC x Auxerre - 29/11 18:00 - SportTV 3",
      "pubDate": "Sat, 29 Nov 2025 18:00:00",
      "guid": ""
    },
    {
      "title": "Águas Santas (Andebol) x Póvoa AC (Andebol) - 29/11 18:30 - AndebolTV",
      "link": "http://www.zerozero.pt/zapping",
      "description": "Águas Santas (Andebol) x Póvoa AC (Andebol) - 29/11 18:30 - AndebolTV",
      "pubDate": "Sat, 29 Nov 2025 18:30:00",
      "guid": ""
    },
    {
      "title": "New York Rangers (Hóquei no Gelo  Seniores) x Tampa Bay Lightning (Hóquei no Gelo  Seniores) - 29/11 19:00 - SportTV 6",
      "link": "http://www.zerozero.pt/zapping",
      "description": "New York Rangers (Hóquei no Gelo  Seniores) x Tampa Bay Lightning (Hóquei no Gelo  Seniores) - 29/11 19:00 - SportTV 6",
      "pubDate": "Sat, 29 Nov 2025 19:00:00",
      "guid": ""
    },
    {
      "title": "Milan x Lazio - 29/11 19:45 - SportTV 7",
      "link": "http://www.zerozero.pt/zapping",
      "description": "Milan x Lazio - 29/11 19:45 - SportTV 7",
      "pubDate": "Sat, 29 Nov 2025 19:45:00",
      "guid": ""
    },
    {
      "title": "ADCR Caxinas Poça Barca (Futsal) x Eléctrico (Futsal) - 29/11 20:00 - C11 Stream",
      "link": "http://www.zerozero.pt/zapping",
      "description": "ADCR Caxinas Poça Barca (Futsal) x Eléctrico (Futsal) - 29/11 20:00 - C11 Stream",
      "pubDate": "Sat, 29 Nov 2025 20:00:00",
      "guid": ""
    },
    {
      "title": "AD Fundão (Futsal) x FC Famalicão (Futsal) - 29/11 20:00 - C11 Stream",
      "link": "http://www.zerozero.pt/zapping",
      "description": "AD Fundão (Futsal) x FC Famalicão (Futsal) - 29/11 20:00 - C11 Stream",
      "pubDate": "Sat, 29 Nov 2025 20:00:00",
      "guid": ""
    },
    {
      "title": "Sporting (Futsal) x Leões Porto Salvo (Futsal) - 29/11 20:00 - Canal11",
      "link": "http://www.zerozero.pt/zapping",
      "description": "Sporting (Futsal) x Leões Porto Salvo (Futsal) - 29/11 20:00 - Canal11",
      "pubDate": "Sat, 29 Nov 2025 20:00:00",
      "guid": ""
    },
    {
      "title": "Benfica (Futsal) x Torreense (Futsal) - 29/11 20:00 - C11 Stream",
      "link": "http://www.zerozero.pt/zapping",
      "description": "Benfica (Futsal) x Torreense (Futsal) - 29/11 20:00 - C11 Stream",
      "pubDate": "Sat, 29 Nov 2025 20:00:00",
      "guid": ""
    },
    {
      "title": "Ferreira do Zêzere (Futsal) x SC Braga (Futsal) - 29/11 20:00 - C11 Stream",
      "link": "http://www.zerozero.pt/zapping",
      "description": "Ferreira do Zêzere (Futsal) x SC Braga (Futsal) - 29/11 20:00 - C11 Stream",
      "pubDate": "Sat, 29 Nov 2025 20:00:00",
      "guid": ""
    },
    {
      "title": "Rio Ave (Futsal) x Quinta dos Lombos (Futsal) - 29/11 20:00 - C11 Stream",
      "link": "http://www.zerozero.pt/zapping",
      "description": "Rio Ave (Futsal) x Quinta dos Lombos (Futsal) - 29/11 20:00 - C11 Stream",
      "pubDate": "Sat, 29 Nov 2025 20:00:00",
      "guid": ""
    },
    {
      "title": "Tottenham x Fulham - 29/11 20:00 - DAZN 1",
      "link": "http://www.zerozero.pt/zapping",
      "description": "Tottenham x Fulham - 29/11 20:00 - DAZN 1",
      "pubDate": "Sat, 29 Nov 2025 20:00:00",
      "guid": ""
    },
    {
      "title": "Atlético de Madrid x Real Oviedo - 29/11 20:00 - DAZN 2",
      "link": "http://www.zerozero.pt/zapping",
      "description": "Atlético de Madrid x Real Oviedo - 29/11 20:00 - DAZN 2",
      "pubDate": "Sat, 29 Nov 2025 20:00:00",
      "guid": ""
    },
    {
      "title": "Valladolid x Málaga - 29/11 20:00 - DAZN 3",
      "link": "http://www.zerozero.pt/zapping",
      "description": "Valladolid x Málaga - 29/11 20:00 - DAZN 3",
      "pubDate": "Sat, 29 Nov 2025 20:00:00",
      "guid": ""
    },
    {
      "title": "Marseille x Toulouse - 29/11 20:05 - SportTV 4",
      "link": "http://www.zerozero.pt/zapping",
      "description": "Marseille x Toulouse - 29/11 20:05 - SportTV 4",
      "pubDate": "Sat, 29 Nov 2025 20:05:00",
      "guid": ""
    },
    {
      "title": "Gil Vicente x CD Tondela - 29/11 20:30 - SportTV 3",
      "link": "http://www.zerozero.pt/zapping",
      "description": "Gil Vicente x CD Tondela - 29/11 20:30 - SportTV 3",
      "pubDate": "Sat, 29 Nov 2025 20:30:00",
      "guid": ""
    }
  ]
}