{
  "items": [
    {
      "title": "Roma (Feminino) x Sporting (Feminino) - 11/09 19:30 - Canal11",
      "link": "http://www.zerozero.pt/zapping",
      "description": "Roma (Feminino) x Sporting (Feminino) - 11/09 19:30 - Canal11",
      "pubDate": "Thu, 11 Sep 2025 19:30:00",
      "guid": ""
    },
    {
      "title": "Portugal (Hóquei Feminino) x Inglaterra (Hóquei Feminino) - 11/09 19:30 - DAZN 1",
      "link": "http://www.zerozero.pt/zapping",
      "description": "Portugal (Hóquei Feminino) x Inglaterra (Hóquei Feminino) - 11/09 19:30 - DAZN 1",
      "pubDate": "Thu, 11 Sep 2025 19:30:00",
      "guid": ""
    },
    {
      "title": "Derrotado 2A/3B x Suíça (Hóquei Feminino) - 12/09 11:00 - DAZN 1",
      "link": "http://www.zerozero.pt/zapping",
      "description": "Derrotado 2A/3B x Suíça (Hóquei Feminino) - 12/09 11:00 - DAZN 1",
      "pubDate": "Fri, 12 Sep 2025 11:00:00",
      "guid": ""
    },
    {
      "title": "Portugal (Praia Feminino) x Polónia (Praia Feminino) - 12/09 11:45 - SportTV 1",
      "link": "http://www.zerozero.pt/zapping",
      "description": "Portugal (Praia Feminino) x Polónia (Praia Feminino) - 12/09 11:45 - SportTV 1",
      "pubDate": "Fri, 12 Sep 2025 11:45:00",
      "guid": ""
    },
    {
      "title": "Filipinas (Voleibol) x Tunísia (Voleibol) - 12/09 12:00 - RTP Play",
      "link": "http://www.zerozero.pt/zapping",
      "description": "Filipinas (Voleibol) x Tunísia (Voleibol) - 12/09 12:00 - RTP Play",
      "pubDate": "Fri, 12 Sep 2025 12:00:00",
      "guid": ""
    },
    {
      "title": "Estoril Praia (S23) x Sporting (S23) - 12/09 12:00 - Canal11",
      "link": "http://www.zerozero.pt/zapping",
      "description": "Estoril Praia (S23) x Sporting (S23) - 12/09 12:00 - Canal11",
      "pubDate": "Fri, 12 Sep 2025 12:00:00",
      "guid": ""
    },
    {
      "title": "Portugal (Praia) x França (Praia) - 12/09 13:00 - SportTV +",
      "link": "http://www.zerozero.pt/zapping",
      "description": "Portugal (Praia) x França (Praia) - 12/09 13:00 - SportTV +",
      "pubDate": "Fri, 12 Sep 2025 13:00:00",
      "guid": ""
    },
    {
      "title": "Países Baixos (Hóquei Feminino) x Alemanha (Hóquei Feminino) - 12/09 14:00 - DAZN 1",
      "link": "http://www.zerozero.pt/zapping",
      "description": "Países Baixos (Hóquei Feminino) x Alemanha (Hóquei Feminino) - 12/09 14:00 - DAZN 1",
      "pubDate": "Fri, 12 Sep 2025 14:00:00",
      "guid": ""
    },
    {
      "title": "2A/3B x Itália (Hóquei Feminino) - 12/09 17:00 - DAZN 3",
      "link": "http://www.zerozero.pt/zapping",
      "description": "2A/3B x Itália (Hóquei Feminino) - 12/09 17:00 - DAZN 3",
      "pubDate": "Fri, 12 Sep 2025 17:00:00",
      "guid": ""
    },
    {
      "title": "SC Paderborn 07 x VfL Bochum - 12/09 17:30 - DAZN 1",
      "link": "http://www.zerozero.pt/zapping",
      "description": "SC Paderborn 07 x VfL Bochum - 12/09 17:30 - DAZN 1",
      "pubDate": "Fri, 12 Sep 2025 17:30:00",
      "guid": ""
    },
    {
      "title": "Al-Ittihad Jeddah x Al-Fateh - 12/09 19:00 - SportTV 2",
      "link": "http://www.zerozero.pt/zapping",
      "description": "Al-Ittihad Jeddah x Al-Fateh - 12/09 19:00 - SportTV 2",
      "pubDate": "Fri, 12 Sep 2025 19:00:00",
      "guid": ""
    },
    {
      "title": "Bayer Leverkusen x Eintracht Frankfurt - 12/09 19:30 - DAZN 1",
      "link": "http://www.zerozero.pt/zapping",
      "description": "Bayer Leverkusen x Eintracht Frankfurt - 12/09 19:30 - DAZN 1",
      "pubDate": "Fri, 12 Sep 2025 19:30:00",
      "guid": ""
    },
    {
      "title": "Espanha (Hóquei Feminino) x França (Hóquei Feminino) - 12/09 19:30 - DAZN 3",
      "link": "http://www.zerozero.pt/zapping",
      "description": "Espanha (Hóquei Feminino) x França (Hóquei Feminino) - 12/09 19:30 - DAZN 3",
      "pubDate": "Fri, 12 Sep 2025 19:30:00",
      "guid": ""
    },
    {
      "title": "Marseille x Lorient - 12/09 19:45 - SportTV 3",
      "link": "http://www.zerozero.pt/zapping",
      "description": "Marseille x Lorient - 12/09 19:45 - SportTV 3",
      "pubDate": "Fri, 12 Sep 2025 19:45:00",
      "guid": ""
    },
    {
      "title": "Ipswich Town x Sheffield United - 12/09 20:00 - SportTV 4",
      "link": "http://www.zerozero.pt/zapping",
      "description": "Ipswich Town x Sheffield United - 12/09 20:00 - SportTV 4",
      "pubDate": "Fri, 12 Sep 2025 20:00:00",
      "guid": ""
    },
    {
      "title": "Sevilla x Elche - 12/09 20:00 - DAZN 2",
      "link": "http://www.zerozero.pt/zapping",
      "description": "Sevilla x Elche - 12/09 20:00 - DAZN 2",
      "pubDate": "Fri, 12 Sep 2025 20:00:00",
      "guid": ""
    },
    {
      "title": "Varzim x USC Paredes - 12/09 20:00 - Canal11",
      "link": "http://www.zerozero.pt/zapping",
      "description": "Varzim x USC Paredes - 12/09 20:00 - Canal11",
      "pubDate": "Fri, 12 Sep 2025 20:00:00",
      "guid": ""
    },
    {
      "title": "Benfica x Santa Clara - 12/09 20:15 - BTv",
      "link": "http://www.zerozero.pt/zapping",
      "description": "Benfica x Santa Clara - 12/09 20:15 - BTv",
      "pubDate": "Fri, 12 Sep 2025 20:15:00",
      "guid": ""
    },
    {
      "title": "FC Alverca x CD Tondela - 12/09 20:15 - SportTV 1",
      "link": "http://www.zerozero.pt/zapping",
      "description": "FC Alverca x CD Tondela - 12/09 20:15 - SportTV 1",
      "pubDate": "Fri, 12 Sep 2025 20:15:00",
      "guid": ""
    },
    {
      "title": "Arsenal da Devesa (Andebol) x FC Porto (Andebol) - 12/09 21:00 - PortoCanal",
      "link": "http://www.zerozero.pt/zapping",
      "description": "Arsenal da Devesa (Andebol) x FC Porto (Andebol) - 12/09 21:00 - PortoCanal",
      "pubDate": "Fri, 12 Sep 2025 21:00:00",
      "guid": ""
    },
    {
      "title": "Racing Club x San Lorenzo - 12/09 23:00 - SportTV 1",
      "link": "http://www.zerozero.pt/zapping",
      "description": "Racing Club x San Lorenzo - 12/09 23:00 - SportTV 1",
      "pubDate": "Fri, 12 Sep 2025 23:00:00",
      "guid": ""
    },
    {
      "title": "Estados Unidos (Voleibol) x Colômbia (Voleibol) - 13/09 03:00 - RTP Play",
      "link": "http://www.zerozero.pt/zapping",
      "description": "Estados Unidos (Voleibol) x Colômbia (Voleibol) - 13/09 03:00 - RTP Play",
      "pubDate": "Sat, 13 Sep 2025 03:00:00",
      "guid": ""
    },
    {
      "title": "Canadá (Voleibol) x Líbia (Voleibol) - 13/09 03:30 - RTP Play",
      "link": "http://www.zerozero.pt/zapping",
      "description": "Canadá (Voleibol) x Líbia (Voleibol) - 13/09 03:30 - RTP Play",
      "pubDate": "Sat, 13 Sep 2025 03:30:00",
      "guid": ""
    },
    {
      "title": "Cuba (Voleibol) x Portugal (Voleibol) - 13/09 06:30 - RTP2",
      "link": "http://www.zerozero.pt/zapping",
      "description": "Cuba (Voleibol) x Portugal (Voleibol) - 13/09 06:30 - RTP2",
      "pubDate": "Sat, 13 Sep 2025 06:30:00",
      "guid": ""
    },
    {
      "title": "Japão (Voleibol) x Turquia (Voleibol) - 13/09 07:00 - RTP Play",
      "link": "http://www.zerozero.pt/zapping",
      "description": "Japão (Voleibol) x Turquia (Voleibol) - 13/09 07:00 - RTP Play",
      "pubDate": "Sat, 13 Sep 2025 07:00:00",
      "guid": ""
    },
    {
      "title": "Alemanha (Voleibol) x Bulgária (Voleibol) - 13/09 10:30 - RTP Play",
      "link": "http://www.zerozero.pt/zapping",
      "description": "Alemanha (Voleibol) x Bulgária (Voleibol) - 13/09 10:30 - RTP Play",
      "pubDate": "Sat, 13 Sep 2025 10:30:00",
      "guid": ""
    },
    {
      "title": "FC Felgueiras x Benfica - 13/09 11:00 - SportTV 1",
      "link": "http://www.zerozero.pt/zapping",
      "description": "FC Felgueiras x Benfica - 13/09 11:00 - SportTV 1",
      "pubDate": "Sat, 13 Sep 2025 11:00:00",
      "guid": ""
    },
    {
      "title": "Países Baixos (Voleibol) x Catar (Voleibol) - 13/09 11:00 - RTP Play",
      "link": "http://www.zerozero.pt/zapping",
      "description": "Países Baixos (Voleibol) x Catar (Voleibol) - 13/09 11:00 - RTP Play",
      "pubDate": "Sat, 13 Sep 2025 11:00:00",
      "guid": ""
    },
    {
      "title": "Benfica (S23) x Est. Amadora (S23) - 13/09 11:00 - Canal11",
      "link": "http://www.zerozero.pt/zapping",
      "description": "Benfica (S23) x Est. Amadora (S23) - 13/09 11:00 - Canal11",
      "pubDate": "Sat, 13 Sep 2025 11:00:00",
      "guid": ""
    },
    {
      "title": "Derrotado RQ5/8 1 x Derrotado RQ5/8 2 - 13/09 11:00 - DAZN 4",
      "link": "http://www.zerozero.pt/zapping",
      "description": "Derrotado RQ5/8 1 x Derrotado RQ5/8 2 - 13/09 11:00 - DAZN 4",
      "pubDate": "Sat, 13 Sep 2025 11:00:00",
      "guid": ""
    },
    {
      "title": "Schalke 04 x Holstein Kiel - 13/09 12:00 - DAZN 3",
      "link": "http://www.zerozero.pt/zapping",
      "description": "Schalke 04 x Holstein Kiel - 13/09 12:00 - DAZN 3",
      "pubDate": "Sat, 13 Sep 2025 12:00:00",
      "guid": ""
    },
    {
      "title": "Arsenal x Nottingham Forest - 13/09 12:30 - DAZN 1",
      "link": "http://www.zerozero.pt/zapping",
      "description": "Arsenal x Nottingham Forest - 13/09 12:30 - DAZN 1",
      "pubDate": "Sat, 13 Sep 2025 12:30:00",
      "guid": ""
    },
    {
      "title": "Getafe x Real Oviedo - 13/09 13:00 - DAZN 2",
      "link": "http://www.zerozero.pt/zapping",
      "description": "Getafe x Real Oviedo - 13/09 13:00 - DAZN 2",
      "pubDate": "Sat, 13 Sep 2025 13:00:00",
      "guid": ""
    },
    {
      "title": "Lusitânia de Lourosa x FC Penafiel - 13/09 14:00 - SportTV +",
      "link": "http://www.zerozero.pt/zapping",
      "description": "Lusitânia de Lourosa x FC Penafiel - 13/09 14:00 - SportTV +",
      "pubDate": "Sat, 13 Sep 2025 14:00:00",
      "guid": ""
    },
    {
      "title": "Cagliari x Parma - 13/09 14:00 - SportTV 6",
      "link": "http://www.zerozero.pt/zapping",
      "description": "Cagliari x Parma - 13/09 14:00 - SportTV 6",
      "pubDate": "Sat, 13 Sep 2025 14:00:00",
      "guid": ""
    },
    {
      "title": "Eslovénia (Voleibol) x Chile (Voleibol) - 13/09 14:00 - RTP Play",
      "link": "http://www.zerozero.pt/zapping",
      "description": "Eslovénia (Voleibol) x Chile (Voleibol) - 13/09 14:00 - RTP Play",
      "pubDate": "Sat, 13 Sep 2025 14:00:00",
      "guid": ""
    },
    {
      "title": "Polónia (Voleibol) x Roménia (Voleibol) - 13/09 14:30 - RTP Play",
      "link": "http://www.zerozero.pt/zapping",
      "description": "Polónia (Voleibol) x Roménia (Voleibol) - 13/09 14:30 - RTP Play",
      "pubDate": "Sat, 13 Sep 2025 14:30:00",
      "guid": ""
    },
    {
      "title": "1. FC Heidenheim 1846 x Borussia Dortmund - 13/09 14:30 - DAZN 4",
      "link": "http://www.zerozero.pt/zapping",
      "description": "1. FC Heidenheim 1846 x Borussia Dortmund - 13/09 14:30 - DAZN 4",
      "pubDate": "Sat, 13 Sep 2025 14:30:00",
      "guid": ""
    },
    {
      "title": "Newcastle x Wolverhampton - 13/09 15:00 - DAZN 2",
      "link": "http://www.zerozero.pt/zapping",
      "description": "Newcastle x Wolverhampton - 13/09 15:00 - DAZN 2",
      "pubDate": "Sat, 13 Sep 2025 15:00:00",
      "guid": ""
    },
    {
      "title": "Fulham x Leeds United - 13/09 15:00 - DAZN 3",
      "link": "http://www.zerozero.pt/zapping",
      "description": "Fulham x Leeds United - 13/09 15:00 - DAZN 3",
      "pubDate": "Sat, 13 Sep 2025 15:00:00",
      "guid": ""
    },
    {
      "title": "Belenenses (Andebol) x ABC (Andebol) - 13/09 15:00 - AndebolTV",
      "link": "http://www.zerozero.pt/zapping",
      "description": "Belenenses (Andebol) x ABC (Andebol) - 13/09 15:00 - AndebolTV",
      "pubDate": "Sat, 13 Sep 2025 15:00:00",
      "guid": ""
    },
    {
      "title": "FC Gaia (Andebol) x Marítimo (Andebol) - 13/09 15:00 - ABola TV",
      "link": "http://www.zerozero.pt/zapping",
      "description": "FC Gaia (Andebol) x Marítimo (Andebol) - 13/09 15:00 - ABola TV",
      "pubDate": "Sat, 13 Sep 2025 15:00:00",
      "guid": ""
    },
    {
      "title": "Real Sociedad x Real Madrid - 13/09 15:15 - DAZN 1",
      "link": "http://www.zerozero.pt/zapping",
      "description": "Real Sociedad x Real Madrid - 13/09 15:15 - DAZN 1",
      "pubDate": "Sat, 13 Sep 2025 15:15:00",
      "guid": ""
    },
    {
      "title": "Moreirense x Rio Ave - 13/09 15:30 - TVI",
      "link": "http://www.zerozero.pt/zapping",
      "description": "Moreirense x Rio Ave - 13/09 15:30 - TVI",
      "pubDate": "Sat, 13 Sep 2025 15:30:00",
      "guid": ""
    },
    {
      "title": "Estoril Praia x AFS - 13/09 15:30 - SportTV 1",
      "link": "http://www.zerozero.pt/zapping",
      "description": "Estoril Praia x AFS - 13/09 15:30 - SportTV 1",
      "pubDate": "Sat, 13 Sep 2025 15:30:00",
      "guid": ""
    },
    {
      "title": "Leixões x Farense - 13/09 15:30 - SportTV 4",
      "link": "http://www.zerozero.pt/zapping",
      "description": "Leixões x Farense - 13/09 15:30 - SportTV 4",
      "pubDate": "Sat, 13 Sep 2025 15:30:00",
      "guid": ""
    },
    {
      "title": "Vitória SC (B) x SC Braga - 13/09 15:30 - Canal11",
      "link": "http://www.zerozero.pt/zapping",
      "description": "Vitória SC (B) x SC Braga - 13/09 15:30 - Canal11",
      "pubDate": "Sat, 13 Sep 2025 15:30:00",
      "guid": ""
    },
    {
      "title": "Trofense x Fafe - 13/09 15:30 - C11 Stream",
      "link": "http://www.zerozero.pt/zapping",
      "description": "Trofense x Fafe - 13/09 15:30 - C11 Stream",
      "pubDate": "Sat, 13 Sep 2025 15:30:00",
      "guid": ""
    },
    {
      "title": "AD Sanjoanense x S. João Ver - 13/09 15:30 - C11 Stream",
      "link": "http://www.zerozero.pt/zapping",
      "description": "AD Sanjoanense x S. João Ver - 13/09 15:30 - C11 Stream",
      "pubDate": "Sat, 13 Sep 2025 15:30:00",
      "guid": ""
    }
  ]
}